setup.cfg
setup.py
Agora_Stoa_Client.egg-info/PKG-INFO
Agora_Stoa_Client.egg-info/SOURCES.txt
Agora_Stoa_Client.egg-info/dependency_links.txt
Agora_Stoa_Client.egg-info/namespace_packages.txt
Agora_Stoa_Client.egg-info/requires.txt
Agora_Stoa_Client.egg-info/top_level.txt
agora/__init__.py
agora/stoa/__init__.py
agora/stoa/client/__init__.py
agora/stoa/client/cli.py