Metadata-Version: 1.1
Name: Agora-Stoa-Client
Version: 0.2.2
Summary: Python-based client to interact with a cluster of Agora Stoas
Home-page: https://github.com/smartdeveloperhub/agora-stoa-client
Author: Fernando Serena
Author-email: fernando.serena@centeropenmiddleware.com
License: Apache 2
Download-URL: https://github.com/smartdeveloperhub/agora-stoa-client/tarball/0.1.0
Keywords: linked-data,ontology,fragments
Platform: UNKNOWN
